appmod_catalog_blueprints/__init__.py
appmod_catalog_blueprints/py.typed
appmod_catalog_blueprints/_jsii/__init__.py
appmod_catalog_blueprints/_jsii/cdk-appmod-catalog-blueprints@1.6.1.jsii.tgz
appmod_catalog_blueprints-1.6.1.dist-info/LICENSE
appmod_catalog_blueprints-1.6.1.dist-info/METADATA
appmod_catalog_blueprints-1.6.1.dist-info/WHEEL
appmod_catalog_blueprints-1.6.1.dist-info/top_level.txt
appmod_catalog_blueprints-1.6.1.dist-info/RECORD
